[
    {
        "schemaVersion": {
            "major": 6,
            "minor": 4,
            "patch": 1
        },
        "fwVersion": {
            "major": 4,
            "minor": 37,
            "patch": 7
        },
        "hwVersion": {
            "major": 6,
            "minor": 0,
            "patch": 2
        },
        "algoVersion": {
            "major": 11,
            "minor": 8,
            "patch": 0
        },
        "timezone": 7200,
        "enrollment": {
            "participantID": "08",
            "siteID": "1",
            "studyID": "1",
            "organizationID": "1974"
        },
        "deviceSn": "3YK3K1542H",
        "deviceModel": "EMBRACEPLUS",
        "rawData": {
            "accelerometer": {
                "timestampStart": 1746908647073930,
                "samplingFrequency": 64.08096313476562,
                "imuParams": {
                    "physicalMin": -16,
                    "physicalMax": 16,
                    "digitalMin": -32768,
                    "digitalMax": 32768
                },
                "x": [
                    737,
                    600,
                    348,
                    173,
                    -27,
                    -173,
                    -148,
                    -74,
                    29,
                    21,
                    68,
                    113,
                    214,
                    301,
                    403,
                    509,
                    646,
                    743,
                    938,
                    1155,
                    1344,
                    1584,
                    1823,
                    1825,
                    1740,
                    1696,
                    1654,
                    1644,
                    1551,
                    1497,
                    1395,
                    1280,
                    1219,
                    1182,
                    1156,
                    1200,
                    1137,
                    1067,
                    1023,
                    990,
                    1025,
                    1091,
                    1183,
                    1277,
                    1303,
                    1274,
                    1199,
                    1123,
                    1034,
                    973,
                    959,
                    974,
                    973,
                    980,
                    1005,
                    1004,
                    1031,
                    1032,
                    1028,
                    997,
                    986,
                    979,
                    954,
                    928,
                    929,
                    949,
                    1014,
                    1062,
                    1080,
                    1130,
                    1184,
                    1241,
                    1266,
                    1298,
                    1412,
                    1563,
                    1762,
                    1773,
                    1502,
                    1385,
                    1380,
                    1393,
                    1314,
                    1176,
                    950,
                    855,
                    814,
                    785,
                    768,
                    792,
                    828,
                    824,
                    786,
                    824,
                    878,
                    876,
                    806,
                    753,
                    685,
                    676,
                    701,
                    821,
                    969,
                    1118,
                    1301,
                    1327,
                    1365,
                    1360,
                    1340,
                    1315,
                    1307,
                    1301,
                    1285,
                    1282,
                    1355,
                    1409,
                    1353,
                    1209,
                    1112,
                    1017,
                    981,
                    1008,
                    1027,
                    1088,
                    1083,
                    1145,
                    1178,
                    1174,
                    1155,
                    1144,
                    1126,
                    1028,
                    963,
                    927,
                    945,
                    978,
                    999,
                    1082,
                    1120,
                    1145,
                    1150,
                    1128,
                    1121,
                    1075,
                    1080,
                    1079,
                    1101,
                    1172,
                    1192,
                    1203,
                    1235,
                    1253,
                    1311,
                    1353,
                    1478,
                    1630,
                    1743,
                    1643,
                    1275,
                    1186,
                    1366,
                    1452,
                    1352,
                    1144,
                    885,
                    838,
                    811,
                    768,
                    730,
                    722,
                    823,
                    925,
                    1003,
                    1036,
                    990,
                    940,
                    909,
                    867,
                    875,
                    878,
                    900,
                    955,
                    1051,
                    1164,
                    1215,
                    1216,
                    1184,
                    1174,
                    1192,
                    1221,
                    1280,
                    1268,
                    1261,
                    1261,
                    1246,
                    1202,
                    1131,
                    1048,
                    1061,
                    1095,
                    1243,
                    1325,
                    1397,
                    1396,
                    1398,
                    1403,
                    1408,
                    1419,
                    1481,
                    1520,
                    1562,
                    1572,
                    1562,
                    1517,
                    1443,
                    1309,
                    1184,
                    980,
                    849,
                    771,
                    735,
                    742,
                    806,
                    900,
                    984,
                    1094,
                    1171,
                    1212,
                    1210,
                    1194,
                    1134,
                    1090,
                    1031,
                    1012,
                    1027,
                    1066,
                    1091,
                    1145,
                    1193,
                    1246,
                    1281,
                    1248,
                    1198,
                    1215,
                    1335,
                    1496,
                    1865,
                    2020,
                    1725,
                    1553,
                    1527,
                    1493,
                    1370,
                    1145,
                    1058,
                    1034,
                    996,
                    916,
                    806,
                    792,
                    741,
                    744,
                    730,
                    733,
                    758,
                    748,
                    742,
                    736,
                    769,
                    787,
                    840,
                    905,
                    994,
                    1101,
                    1168,
                    1209,
                    1265,
                    1278,
                    1274,
                    1279,
                    1235,
                    1224,
                    1222,
                    1237,
                    1273,
                    1335,
                    1485,
                    1508,
                    1457,
                    1463,
                    1552,
                    1678,
                    1779,
                    1840,
                    1818,
                    1758,
                    1612,
                    1452,
                    1287,
                    1069,
                    978,
                    886,
                    843,
                    835,
                    885,
                    981,
                    1053,
                    1104,
                    1078,
                    1113,
                    1117,
                    1100,
                    1086,
                    1054,
                    1020,
                    1041,
                    1102,
                    1179,
                    1255,
                    1374,
                    1412,
                    1401,
                    1406,
                    1564,
                    1867,
                    2029,
                    1916,
                    1514,
                    1259,
                    1353,
                    1397,
                    1298,
                    1044,
                    912,
                    830,
                    842,
                    827,
                    811,
                    821,
                    925,
                    993,
                    1041,
                    1058,
                    1003,
                    936,
                    881,
                    812,
                    785,
                    770,
                    799,
                    840,
                    926,
                    1047,
                    1123,
                    1139,
                    1101,
                    1041,
                    999,
                    998,
                    1010,
                    1056,
                    1121,
                    1199,
                    1230,
                    1254,
                    1221,
                    1293,
                    1418,
                    1530,
                    1525,
                    1440,
                    1431,
                    1513,
                    1605,
                    1595,
                    1698,
                    1620,
                    1519,
                    1411,
                    1229,
                    1148,
                    1072,
                    1016,
                    972,
                    915,
                    846,
                    812,
                    793,
                    794,
                    849,
                    905,
                    970,
                    976,
                    978,
                    1008,
                    981,
                    972,
                    984,
                    968,
                    1024,
                    1079,
                    1126,
                    1204,
                    1233,
                    1243,
                    1244,
                    1287,
                    1416,
                    1628,
                    1826,
                    1723,
                    1478,
                    1420,
                    1547,
                    1604,
                    1316,
                    1082,
                    939,
                    914,
                    978,
                    1005,
                    1015,
                    984,
                    934,
                    887,
                    843,
                    823,
                    762,
                    711,
                    699,
                    710,
                    712,
                    754,
                    822,
                    920,
                    1015,
                    1075,
                    1058,
                    1002,
                    992,
                    1037,
                    1133,
                    1234,
                    1304,
                    1337,
                    1369,
                    1346,
                    1314,
                    1311,
                    1337,
                    1384,
                    1506,
                    1486,
                    1365,
                    1262,
                    1179,
                    1168,
                    1171,
                    1251,
                    1310,
                    1349,
                    1385,
                    1389,
                    1337,
                    1217,
                    1047,
                    922,
                    812,
                    726,
                    709,
                    701,
                    761,
                    807,
                    886,
                    950,
                    1016,
                    1004,
                    1017,
                    1026,
                    1041,
                    1033,
                    1035,
                    1041,
                    1023,
                    1091,
                    1186,
                    1253,
                    1288,
                    1334,
                    1342,
                    1340,
                    1285,
                    1245,
                    1271,
                    1331,
                    1374,
                    1487,
                    1576,
                    1491,
                    1403,
                    1442,
                    1504,
                    1391,
                    1188,
                    988,
                    893,
                    847,
                    827,
                    779,
                    754,
                    770,
                    858,
                    919,
                    929,
                    837,
                    748,
                    684,
                    656,
                    653,
                    641,
                    661,
                    733,
                    772,
                    882,
                    1019,
                    1105,
                    1177,
                    1215,
                    1206,
                    1203,
                    1234,
                    1299,
                    1339,
                    1366,
                    1364,
                    1303,
                    1248,
                    1156,
                    1102,
                    1085,
                    1138,
                    1315,
                    1390,
                    1407,
                    1338,
                    1325,
                    1297,
                    1278,
                    1288,
                    1319,
                    1294,
                    1250,
                    1192,
                    1178,
                    1127,
                    1082,
                    1000,
                    928,
                    869,
                    847,
                    833,
                    824,
                    849,
                    851,
                    895,
                    939,
                    971,
                    1008,
                    1046,
                    1085,
                    1105,
                    1131,
                    1111,
                    1118,
                    1118,
                    1110,
                    1125,
                    1166,
                    1191,
                    1217,
                    1231,
                    1236,
                    1236,
                    1214,
                    1211,
                    1267,
                    1285,
                    1359,
                    1508,
                    1605,
                    1509,
                    1400,
                    1414,
                    1460,
                    1359,
                    1210,
                    1083,
                    1056,
                    1046,
                    1029,
                    1029,
                    1024,
                    996,
                    1041,
                    1001,
                    987,
                    924,
                    824,
                    775,
                    713,
                    667,
                    656,
                    674,
                    694,
                    799,
                    908,
                    1007,
                    1116,
                    1165,
                    1200,
                    1179,
                    1169,
                    1210,
                    1261,
                    1291,
                    1333,
                    1337,
                    1260,
                    1185,
                    1152,
                    1102,
                    1131,
                    1139,
                    1172,
                    1164,
                    1119,
                    1086,
                    1120,
                    1236,
                    1347
                ],
                "y": [
                    -950,
                    -1028,
                    -1066,
                    -1117,
                    -1156,
                    -1301,
                    -1366,
                    -1346,
                    -1268,
                    -1146,
                    -1044,
                    -953,
                    -926,
                    -905,
                    -883,
                    -858,
                    -791,
                    -748,
                    -653,
                    -560,
                    -515,
                    -466,
                    -326,
                    -201,
                    -105,
                    -54,
                    -83,
                    -119,
                    -281,
                    -373,
                    -454,
                    -554,
                    -599,
                    -633,
                    -695,
                    -807,
                    -861,
                    -859,
                    -859,
                    -886,
                    -927,
                    -942,
                    -995,
                    -1034,
                    -1037,
                    -977,
                    -917,
                    -863,
                    -733,
                    -666,
                    -621,
                    -554,
                    -510,
                    -491,
                    -432,
                    -395,
                    -379,
                    -373,
                    -364,
                    -362,
                    -383,
                    -426,
                    -441,
                    -457,
                    -470,
                    -498,
                    -529,
                    -533,
                    -570,
                    -583,
                    -606,
                    -608,
                    -552,
                    -452,
                    -356,
                    -351,
                    -388,
                    -561,
                    -678,
                    -763,
                    -848,
                    -925,
                    -901,
                    -822,
                    -768,
                    -768,
                    -793,
                    -833,
                    -861,
                    -887,
                    -895,
                    -843,
                    -831,
                    -819,
                    -769,
                    -722,
                    -649,
                    -601,
                    -535,
                    -486,
                    -454,
                    -438,
                    -415,
                    -418,
                    -388,
                    -352,
                    -317,
                    -299,
                    -301,
                    -336,
                    -356,
                    -410,
                    -421,
                    -458,
                    -543,
                    -607,
                    -657,
                    -676,
                    -694,
                    -761,
                    -830,
                    -916,
                    -997,
                    -1060,
                    -1188,
                    -1246,
                    -1269,
                    -1222,
                    -1090,
                    -982,
                    -859,
                    -689,
                    -586,
                    -518,
                    -434,
                    -407,
                    -376,
                    -380,
                    -348,
                    -340,
                    -346,
                    -342,
                    -334,
                    -331,
                    -340,
                    -340,
                    -344,
                    -376,
                    -406,
                    -433,
                    -468,
                    -532,
                    -558,
                    -535,
                    -515,
                    -540,
                    -619,
                    -799,
                    -841,
                    -875,
                    -920,
                    -876,
                    -810,
                    -743,
                    -717,
                    -714,
                    -741,
                    -823,
                    -887,
                    -920,
                    -1014,
                    -1021,
                    -973,
                    -875,
                    -703,
                    -579,
                    -479,
                    -388,
                    -363,
                    -350,
                    -362,
                    -344,
                    -350,
                    -342,
                    -358,
                    -345,
                    -327,
                    -349,
                    -413,
                    -454,
                    -544,
                    -590,
                    -605,
                    -557,
                    -521,
                    -490,
                    -423,
                    -307,
                    -279,
                    -245,
                    -243,
                    -295,
                    -348,
                    -426,
                    -445,
                    -476,
                    -525,
                    -591,
                    -678,
                    -774,
                    -901,
                    -995,
                    -1038,
                    -1036,
                    -964,
                    -858,
                    -743,
                    -613,
                    -497,
                    -437,
                    -398,
                    -391,
                    -366,
                    -369,
                    -403,
                    -445,
                    -484,
                    -526,
                    -523,
                    -493,
                    -461,
                    -436,
                    -422,
                    -392,
                    -358,
                    -352,
                    -351,
                    -364,
                    -390,
                    -415,
                    -385,
                    -320,
                    -240,
                    -171,
                    -136,
                    -178,
                    -399,
                    -693,
                    -832,
                    -909,
                    -1011,
                    -1008,
                    -905,
                    -794,
                    -744,
                    -744,
                    -814,
                    -828,
                    -824,
                    -783,
                    -708,
                    -683,
                    -649,
                    -643,
                    -623,
                    -614,
                    -592,
                    -573,
                    -582,
                    -570,
                    -573,
                    -573,
                    -602,
                    -595,
                    -590,
                    -581,
                    -557,
                    -511,
                    -488,
                    -388,
                    -346,
                    -261,
                    -212,
                    -135,
                    -149,
                    -183,
                    -302,
                    -402,
                    -471,
                    -585,
                    -655,
                    -780,
                    -852,
                    -961,
                    -1006,
                    -1025,
                    -928,
                    -826,
                    -709,
                    -558,
                    -473,
                    -427,
                    -380,
                    -385,
                    -389,
                    -399,
                    -428,
                    -463,
                    -491,
                    -501,
                    -533,
                    -519,
                    -488,
                    -427,
                    -379,
                    -341,
                    -306,
                    -298,
                    -267,
                    -240,
                    -218,
                    -185,
                    -165,
                    -172,
                    -242,
                    -439,
                    -765,
                    -850,
                    -873,
                    -844,
                    -830,
                    -814,
                    -768,
                    -794,
                    -817,
                    -831,
                    -880,
                    -949,
                    -989,
                    -1011,
                    -1031,
                    -1025,
                    -946,
                    -859,
                    -740,
                    -674,
                    -615,
                    -608,
                    -615,
                    -615,
                    -658,
                    -663,
                    -710,
                    -716,
                    -687,
                    -642,
                    -517,
                    -462,
                    -413,
                    -347,
                    -311,
                    -247,
                    -210,
                    -177,
                    -146,
                    -122,
                    -108,
                    -150,
                    -215,
                    -334,
                    -354,
                    -426,
                    -520,
                    -611,
                    -749,
                    -870,
                    -903,
                    -909,
                    -918,
                    -885,
                    -843,
                    -791,
                    -711,
                    -677,
                    -660,
                    -612,
                    -590,
                    -582,
                    -581,
                    -569,
                    -567,
                    -587,
                    -569,
                    -568,
                    -569,
                    -554,
                    -518,
                    -479,
                    -443,
                    -422,
                    -401,
                    -368,
                    -305,
                    -298,
                    -265,
                    -223,
                    -207,
                    -183,
                    -299,
                    -511,
                    -711,
                    -784,
                    -843,
                    -883,
                    -836,
                    -688,
                    -634,
                    -620,
                    -675,
                    -781,
                    -875,
                    -926,
                    -951,
                    -944,
                    -933,
                    -882,
                    -847,
                    -805,
                    -748,
                    -726,
                    -696,
                    -670,
                    -659,
                    -653,
                    -686,
                    -692,
                    -643,
                    -571,
                    -477,
                    -414,
                    -368,
                    -323,
                    -296,
                    -301,
                    -312,
                    -300,
                    -263,
                    -248,
                    -256,
                    -267,
                    -278,
                    -338,
                    -380,
                    -375,
                    -377,
                    -437,
                    -473,
                    -544,
                    -667,
                    -820,
                    -936,
                    -1037,
                    -1106,
                    -1129,
                    -1103,
                    -999,
                    -907,
                    -818,
                    -749,
                    -719,
                    -671,
                    -636,
                    -621,
                    -629,
                    -591,
                    -566,
                    -531,
                    -497,
                    -445,
                    -402,
                    -367,
                    -330,
                    -321,
                    -290,
                    -280,
                    -272,
                    -298,
                    -289,
                    -304,
                    -320,
                    -354,
                    -312,
                    -288,
                    -236,
                    -211,
                    -211,
                    -286,
                    -417,
                    -621,
                    -734,
                    -806,
                    -905,
                    -900,
                    -828,
                    -742,
                    -704,
                    -718,
                    -759,
                    -818,
                    -861,
                    -951,
                    -1010,
                    -1041,
                    -1037,
                    -914,
                    -799,
                    -728,
                    -654,
                    -576,
                    -556,
                    -549,
                    -558,
                    -539,
                    -524,
                    -521,
                    -503,
                    -464,
                    -410,
                    -362,
                    -335,
                    -316,
                    -307,
                    -296,
                    -308,
                    -277,
                    -272,
                    -221,
                    -170,
                    -125,
                    -93,
                    -114,
                    -191,
                    -331,
                    -454,
                    -575,
                    -633,
                    -667,
                    -727,
                    -807,
                    -856,
                    -957,
                    -1001,
                    -1045,
                    -1073,
                    -1048,
                    -995,
                    -928,
                    -877,
                    -838,
                    -812,
                    -774,
                    -718,
                    -667,
                    -634,
                    -603,
                    -576,
                    -569,
                    -537,
                    -516,
                    -507,
                    -486,
                    -467,
                    -474,
                    -442,
                    -441,
                    -424,
                    -413,
                    -389,
                    -377,
                    -355,
                    -346,
                    -334,
                    -328,
                    -328,
                    -322,
                    -303,
                    -301,
                    -321,
                    -381,
                    -544,
                    -704,
                    -762,
                    -825,
                    -849,
                    -821,
                    -759,
                    -766,
                    -802,
                    -846,
                    -905,
                    -995,
                    -987,
                    -1021,
                    -1036,
                    -1005,
                    -932,
                    -875,
                    -780,
                    -717,
                    -658,
                    -586,
                    -565,
                    -543,
                    -560,
                    -583,
                    -591,
                    -599,
                    -574,
                    -521,
                    -477,
                    -392,
                    -369,
                    -320,
                    -281,
                    -278,
                    -293,
                    -332,
                    -347,
                    -328,
                    -339,
                    -370,
                    -389,
                    -417,
                    -487,
                    -573,
                    -584,
                    -620,
                    -656,
                    -715,
                    -815
                ],
                "z": [
                    1874,
                    1894,
                    1838,
                    1743,
                    1652,
                    1611,
                    1633,
                    1698,
                    1686,
                    1601,
                    1519,
                    1477,
                    1551,
                    1601,
                    1637,
                    1633,
                    1629,
                    1646,
                    1699,
                    1764,
                    1812,
                    1773,
                    1712,
                    1642,
                    1589,
                    1569,
                    1595,
                    1591,
                    1571,
                    1603,
                    1642,
                    1749,
                    1818,
                    1945,
                    2150,
                    2430,
                    2367,
                    2151,
                    1731,
                    1462,
                    1275,
                    1193,
                    1280,
                    1408,
                    1505,
                    1685,
                    1704,
                    1666,
                    1595,
                    1537,
                    1512,
                    1521,
                    1507,
                    1472,
                    1404,
                    1422,
                    1419,
                    1437,
                    1399,
                    1392,
                    1389,
                    1429,
                    1439,
                    1450,
                    1470,
                    1543,
                    1628,
                    1705,
                    1800,
                    1876,
                    1940,
                    1948,
                    1897,
                    1819,
                    1831,
                    1947,
                    2057,
                    2201,
                    2101,
                    1962,
                    1858,
                    1753,
                    1700,
                    1664,
                    1666,
                    1680,
                    1733,
                    1752,
                    1721,
                    1680,
                    1628,
                    1592,
                    1533,
                    1506,
                    1514,
                    1540,
                    1509,
                    1449,
                    1443,
                    1462,
                    1482,
                    1553,
                    1592,
                    1589,
                    1610,
                    1629,
                    1656,
                    1677,
                    1740,
                    1834,
                    1930,
                    2013,
                    2022,
                    2044,
                    2197,
                    2241,
                    2118,
                    1766,
                    1537,
                    1383,
                    1319,
                    1318,
                    1414,
                    1522,
                    1613,
                    1685,
                    1741,
                    1770,
                    1754,
                    1702,
                    1613,
                    1535,
                    1500,
                    1471,
                    1428,
                    1397,
                    1364,
                    1329,
                    1315,
                    1311,
                    1334,
                    1373,
                    1383,
                    1374,
                    1406,
                    1430,
                    1479,
                    1577,
                    1623,
                    1703,
                    1756,
                    1833,
                    1864,
                    1864,
                    1928,
                    2027,
                    2183,
                    2281,
                    2243,
                    2136,
                    2021,
                    1888,
                    1716,
                    1570,
                    1565,
                    1572,
                    1600,
                    1647,
                    1677,
                    1698,
                    1646,
                    1617,
                    1600,
                    1562,
                    1463,
                    1429,
                    1408,
                    1414,
                    1398,
                    1388,
                    1423,
                    1460,
                    1508,
                    1547,
                    1559,
                    1582,
                    1570,
                    1594,
                    1629,
                    1661,
                    1722,
                    1773,
                    1826,
                    1857,
                    1886,
                    1863,
                    1804,
                    1780,
                    1878,
                    2033,
                    2166,
                    2136,
                    1981,
                    1687,
                    1491,
                    1305,
                    1189,
                    1167,
                    1193,
                    1338,
                    1483,
                    1541,
                    1614,
                    1685,
                    1717,
                    1709,
                    1676,
                    1624,
                    1567,
                    1520,
                    1466,
                    1418,
                    1405,
                    1381,
                    1402,
                    1419,
                    1451,
                    1477,
                    1521,
                    1554,
                    1556,
                    1549,
                    1532,
                    1549,
                    1564,
                    1627,
                    1696,
                    1742,
                    1759,
                    1777,
                    1774,
                    1713,
                    1656,
                    1640,
                    1707,
                    1824,
                    2034,
                    2229,
                    2314,
                    2345,
                    2106,
                    1875,
                    1704,
                    1646,
                    1662,
                    1752,
                    1860,
                    1822,
                    1697,
                    1577,
                    1426,
                    1351,
                    1341,
                    1367,
                    1356,
                    1349,
                    1346,
                    1354,
                    1395,
                    1424,
                    1441,
                    1453,
                    1465,
                    1488,
                    1544,
                    1590,
                    1669,
                    1739,
                    1796,
                    1856,
                    1814,
                    1768,
                    1739,
                    1792,
                    1840,
                    1902,
                    2020,
                    1935,
                    1732,
                    1420,
                    1349,
                    1368,
                    1460,
                    1578,
                    1626,
                    1624,
                    1618,
                    1601,
                    1539,
                    1467,
                    1425,
                    1399,
                    1376,
                    1347,
                    1349,
                    1383,
                    1399,
                    1437,
                    1499,
                    1586,
                    1623,
                    1624,
                    1586,
                    1545,
                    1525,
                    1519,
                    1544,
                    1607,
                    1677,
                    1754,
                    1770,
                    1758,
                    1770,
                    1866,
                    2085,
                    2299,
                    2259,
                    2026,
                    1870,
                    1704,
                    1647,
                    1602,
                    1591,
                    1621,
                    1691,
                    1722,
                    1719,
                    1685,
                    1630,
                    1541,
                    1491,
                    1509,
                    1515,
                    1512,
                    1465,
                    1461,
                    1435,
                    1435,
                    1446,
                    1451,
                    1432,
                    1476,
                    1503,
                    1534,
                    1536,
                    1515,
                    1479,
                    1512,
                    1589,
                    1676,
                    1725,
                    1757,
                    1792,
                    1785,
                    1744,
                    1779,
                    1927,
                    2087,
                    2159,
                    1985,
                    1706,
                    1493,
                    1397,
                    1479,
                    1536,
                    1670,
                    1762,
                    1792,
                    1758,
                    1701,
                    1684,
                    1666,
                    1638,
                    1628,
                    1576,
                    1581,
                    1557,
                    1545,
                    1539,
                    1561,
                    1564,
                    1569,
                    1554,
                    1555,
                    1576,
                    1545,
                    1503,
                    1469,
                    1477,
                    1534,
                    1603,
                    1661,
                    1731,
                    1765,
                    1767,
                    1762,
                    1816,
                    1899,
                    2080,
                    2155,
                    2048,
                    1851,
                    1648,
                    1550,
                    1519,
                    1560,
                    1658,
                    1718,
                    1770,
                    1772,
                    1745,
                    1675,
                    1594,
                    1554,
                    1569,
                    1578,
                    1539,
                    1529,
                    1527,
                    1534,
                    1543,
                    1559,
                    1554,
                    1554,
                    1556,
                    1566,
                    1559,
                    1548,
                    1553,
                    1542,
                    1579,
                    1650,
                    1756,
                    1803,
                    1792,
                    1739,
                    1695,
                    1694,
                    1783,
                    1843,
                    1915,
                    1963,
                    1844,
                    1670,
                    1518,
                    1383,
                    1387,
                    1449,
                    1547,
                    1611,
                    1673,
                    1751,
                    1812,
                    1830,
                    1849,
                    1785,
                    1730,
                    1681,
                    1678,
                    1672,
                    1677,
                    1686,
                    1683,
                    1652,
                    1640,
                    1615,
                    1581,
                    1550,
                    1534,
                    1510,
                    1494,
                    1510,
                    1484,
                    1465,
                    1483,
                    1561,
                    1635,
                    1690,
                    1746,
                    1787,
                    1803,
                    1774,
                    1715,
                    1696,
                    1777,
                    1880,
                    2001,
                    2101,
                    2087,
                    1975,
                    1910,
                    1812,
                    1707,
                    1639,
                    1648,
                    1683,
                    1717,
                    1766,
                    1766,
                    1723,
                    1680,
                    1642,
                    1615,
                    1619,
                    1564,
                    1545,
                    1554,
                    1547,
                    1566,
                    1532,
                    1534,
                    1536,
                    1569,
                    1578,
                    1606,
                    1627,
                    1637,
                    1633,
                    1615,
                    1614,
                    1651,
                    1696,
                    1762,
                    1816,
                    1799,
                    1758,
                    1709,
                    1663,
                    1670,
                    1789,
                    1928,
                    2098,
                    2129,
                    1999,
                    1791,
                    1676,
                    1574,
                    1492,
                    1517,
                    1603,
                    1655,
                    1739,
                    1752,
                    1743,
                    1758,
                    1756,
                    1741,
                    1675,
                    1623,
                    1603,
                    1573,
                    1543,
                    1515,
                    1507,
                    1507,
                    1531,
                    1524,
                    1504,
                    1503,
                    1473,
                    1460,
                    1470,
                    1476,
                    1473,
                    1493,
                    1504,
                    1542,
                    1591,
                    1604,
                    1622,
                    1645,
                    1675,
                    1700,
                    1710,
                    1725,
                    1739,
                    1769,
                    1835,
                    1956,
                    2012,
                    1942,
                    1816,
                    1759,
                    1711,
                    1657,
                    1642,
                    1664,
                    1744,
                    1778,
                    1770,
                    1714,
                    1679,
                    1654,
                    1643,
                    1590,
                    1556,
                    1521,
                    1499,
                    1524,
                    1495,
                    1490,
                    1487,
                    1482,
                    1498,
                    1528,
                    1563,
                    1588,
                    1602,
                    1597,
                    1595,
                    1609,
                    1658,
                    1676,
                    1725,
                    1761,
                    1739,
                    1739,
                    1702,
                    1673,
                    1743,
                    1860,
                    1960,
                    2068,
                    2092,
                    1974,
                    1770,
                    1606,
                    1451,
                    1403,
                    1443
                ]
            },
            "gyroscope": {
                "timestampStart": 0,
                "samplingFrequency": 0.0,
                "imuParams": {
                    "physicalMin": 0,
                    "physicalMax": 0,
                    "digitalMin": 0,
                    "digitalMax": 0
                },
                "x": [],
                "y": [],
                "z": []
            },
            "eda": {
                "timestampStart": 1746908647308489,
                "samplingFrequency": 3.9976210594177246,
                "values": [
                    -0.02677815966308117,
                    -0.02538013644516468,
                    -0.026340395212173462,
                    -0.025973238050937653,
                    -0.026241544634103775,
                    -0.02641100250184536,
                    -0.025634322315454483,
                    -0.02638275921344757,
                    -0.024095086380839348,
                    -0.025478987023234367,
                    -0.024928251281380653,
                    -0.024137450382113457,
                    -0.02605796605348587,
                    -0.024914128705859184,
                    -0.025648444890975952,
                    -0.026213303208351135,
                    -0.024250421673059464,
                    -0.023953871801495552,
                    -0.024787036702036858,
                    -0.024885887280106544,
                    -0.024631701409816742,
                    -0.026961740106344223,
                    -0.02676403895020485,
                    -0.026495732367038727,
                    -0.025281287729740143,
                    -0.024900007992982864,
                    -0.025577837601304054,
                    -0.024843521416187286,
                    -0.025507230311632156,
                    -0.026636945083737373,
                    -0.025507230311632156,
                    -0.02545074373483658,
                    -0.02608620934188366,
                    -0.02365732006728649,
                    -0.024236299097537994,
                    -0.025210680440068245,
                    -0.024815279990434647,
                    -0.02545074373483658,
                    -0.024871764704585075,
                    -0.025648444890975952
                ]
            },
            "temperature": {
                "timestampStart": 1746908648058641,
                "samplingFrequency": 0.9997071027755737,
                "values": [
                    19.3046875,
                    19.296875,
                    19.3125,
                    19.3125,
                    19.3046875,
                    19.3125,
                    19.296875,
                    19.3046875,
                    19.3203125,
                    19.3125
                ]
            },
            "tags": {
                "tagsTimeMicros": []
            },
            "bvp": {
                "timestampStart": 1746908647061998,
                "samplingFrequency": 64.0,
                "values": [
                    0.0,
                    1.2755393981933594e-05,
                    0.00010543037933530286,
                    0.0005015158094465733,
                    0.0017381453653797507,
                    0.004737851209938526,
                    0.010670029558241367,
                    0.02061462588608265,
                    0.03511124104261398,
                    0.05376701056957245,
                    0.07512892037630081,
                    0.09688396006822586,
                    0.11628424376249313,
                    0.13063810765743256,
                    0.13774186372756958,
                    0.1362089216709137,
                    0.1257096529006958,
                    0.10708927363157272,
                    0.08227059245109558,
                    0.05390845984220505,
                    0.02485593408346176,
                    -0.0024510957300662994,
                    -0.026524994522333145,
                    -0.04710453748703003,
                    -0.06507105380296707,
                    -0.08194684237241745,
                    -0.09909503161907196,
                    -0.11698449403047562,
                    -0.13488197326660156,
                    -0.15103186666965485,
                    -0.16311660408973694,
                    -0.16879014670848846,
                    -0.16615638136863708,
                    -0.15405642986297607,
                    -0.132096067070961,
                    -0.10057041049003601,
                    -0.06056125462055206,
                    -0.014218702912330627,
                    0.03510608151555061,
                    0.08315392583608627,
                    0.12544244527816772,
                    0.1581345498561859,
                    0.178848996758461,
                    0.18713557720184326,
                    0.18440255522727966,
                    0.17334255576133728,
                    0.15713098645210266,
                    0.13868370652198792,
                    0.1201426088809967,
                    0.10263659060001373,
                    0.08629443496465683,
                    0.07044383138418198,
                    0.053923092782497406,
                    0.035447441041469574,
                    0.013932771980762482,
                    -0.011290378868579865,
                    -0.040345653891563416,
                    -0.07276859879493713,
                    -0.10758661478757858,
                    -0.14345648884773254,
                    -0.17874151468276978,
                    -0.21153180301189423,
                    -0.23974207043647766,
                    -0.26135626435279846,
                    -0.2747464179992676,
                    -0.27894777059555054,
                    -0.27382317185401917,
                    -0.2601008713245392,
                    -0.2392699420452118,
                    -0.21334461867809296,
                    -0.18456704914569855,
                    -0.1551312655210495,
                    -0.12698274850845337,
                    -0.10170962661504745,
                    -0.08049453049898148,
                    -0.06408068537712097,
                    -0.05272312089800835,
                    -0.046112410724163055,
                    -0.04332999885082245,
                    -0.04297478869557381,
                    -0.04348702356219292,
                    -0.04348976910114288,
                    -0.041980549693107605,
                    -0.038359299302101135,
                    -0.03236624598503113,
                    -0.024013623595237732,
                    -0.013540111482143402,
                    -0.0013626441359519958,
                    0.011989519000053406,
                    0.02594643458724022,
                    0.039963673800230026,
                    0.05358022451400757,
                    0.0664578229188919,
                    0.07839035987854004,
                    0.08928918838500977,
                    0.09914669394493103,
                    0.10797477513551712,
                    0.11574055999517441,
                    0.12232711911201477,
                    0.12752994894981384,
                    0.13109339773654938,
                    0.1327746957540512,
                    0.13240571320056915,
                    0.12992772459983826,
                    0.1253979355096817,
                    0.11899074167013168,
                    0.11100873351097107,
                    0.10188877582550049,
                    0.09218797087669373,
                    0.08254916965961456,
                    0.0736478716135025,
                    0.06612402200698853,
                    0.060517970472574234,
                    0.057259511202573776,
                    0.0567353218793869,
                    0.05934060364961624,
                    0.06536733359098434,
                    0.074747733771801,
                    0.08685356378555298,
                    0.10049805045127869,
                    0.11412542313337326,
                    0.12610921263694763,
                    0.13508564233779907,
                    0.1402370184659958,
                    0.14142785966396332,
                    0.13914324343204498,
                    0.13426777720451355,
                    0.12779632210731506,
                    0.12056984007358551,
                    0.11309501528739929,
                    0.1054382175207138,
                    0.09716138988733292,
                    0.08734264224767685,
                    0.0747695341706276,
                    0.05828976631164551,
                    0.037190020084381104,
                    0.011484792456030846,
                    -0.01795799471437931,
                    -0.04948819428682327,
                    -0.08090908080339432,
                    -0.10980582982301712,
                    -0.1339007318019867,
                    -0.15138021111488342,
                    -0.16114386916160583,
                    -0.16292999684810638,
                    -0.157292902469635,
                    -0.1454562544822693,
                    -0.129090815782547,
                    -0.11005371809005737,
                    -0.09013321995735168,
                    -0.07084843516349792,
                    -0.05332937836647034,
                    -0.03828047960996628,
                    -0.02601722441613674,
                    -0.016546769067645073,
                    -0.009651624597609043,
                    -0.00494042132049799,
                    -0.001857046503573656,
                    0.00028916168957948685,
                    0.0021841125562787056,
                    0.004298149608075619,
                    0.00675208680331707,
                    0.009334438480436802,
                    0.011621637269854546,
                    0.013130558654665947,
                    0.013458692468702793,
                    0.012391195632517338,
                    0.009974882006645203,
                    0.006544172763824463,
                    0.0026680100709199905,
                    -0.0009777545928955078,
                    -0.003764452412724495,
                    -0.005239551886916161,
                    -0.00520741380751133,
                    -0.003760317340493202,
                    -0.0012548714876174927,
                    0.0017681345343589783,
                    0.004697902128100395,
                    0.0069593265652656555,
                    0.008087728172540665,
                    0.00778406485915184,
                    0.005951600149273872,
                    0.002697063609957695,
                    -0.0017047356814146042,
                    -0.006870221346616745,
                    -0.012381693348288536,
                    -0.01786494255065918,
                    -0.023040611296892166,
                    -0.02772749774158001,
                    -0.031812697649002075,
                    -0.035220395773649216,
                    -0.03789298236370087,
                    -0.039778538048267365,
                    -0.04082386568188667,
                    -0.04098854213953018,
                    -0.040280573070049286,
                    -0.03878170624375343,
                    -0.03663597255945206,
                    -0.0339992418885231,
                    -0.03096141293644905,
                    -0.027480408549308777,
                    -0.023394718766212463,
                    -0.018545741215348244,
                    -0.01294147502630949,
                    -0.006843726150691509,
                    -0.0007310789078474045,
                    0.004827413707971573,
                    0.009349839761853218,
                    0.01262904703617096,
                    0.014858637005090714,
                    0.016635553911328316,
                    0.018808433786034584,
                    0.022199302911758423,
                    0.027307914569973946,
                    0.034122008830308914,
                    0.04209805279970169,
                    0.050295621156692505,
                    0.05758753791451454,
                    0.06286777555942535,
                    0.06521597504615784,
                    0.06400367617607117,
                    0.05894041061401367,
                    0.05007133632898331,
                    0.03774746134877205,
                    0.022588089108467102,
                    0.005440041422843933,
                    -0.012683456763625145,
                    -0.030686013400554657,
                    -0.04747094213962555,
                    -0.06202595680952072,
                    -0.07352383434772491,
                    -0.08142007887363434,
                    -0.08551491796970367,
                    -0.08596503734588623,
                    -0.0832485556602478,
                    -0.07809075713157654,
                    -0.07135850936174393,
                    -0.06394399702548981,
                    -0.05666360631585121,
                    -0.050185371190309525,
                    -0.04497969150543213,
                    -0.041281234472990036,
                    -0.03907687962055206,
                    -0.038146913051605225,
                    -0.03815505653619766,
                    -0.03876104950904846,
                    -0.039695680141448975,
                    -0.040708668529987335,
                    -0.041419100016355515,
                    -0.04126598685979843,
                    -0.03967271372675896,
                    -0.03628965839743614,
                    -0.03112291730940342,
                    -0.02450716122984886,
                    -0.01698966696858406,
                    -0.00918882992118597,
                    -0.001663961447775364,
                    0.005174398422241211,
                    0.011085331439971924,
                    0.015953248366713524,
                    0.01973245106637478,
                    0.02242322824895382,
                    0.02406970225274563,
                    0.024757295846939087,
                    0.02460544928908348,
                    0.023760633543133736,
                    0.022393129765987396,
                    0.020694462582468987,
                    0.018868135288357735,
                    0.017110977321863174,
                    0.015589247457683086,
                    0.014416252262890339,
                    0.013641716912388802,
                    0.013257486745715141,
                    0.013206063769757748,
                    0.013384138233959675,
                    0.013656879775226116,
                    0.013892416842281818,
                    0.014000535011291504,
                    0.013941203244030476,
                    0.013675812631845474,
                    0.013096349313855171,
                    0.012017196044325829,
                    0.010264553129673004,
                    0.007818413898348808,
                    0.004940919578075409,
                    0.0022280681878328323,
                    0.000514935702085495,
                    0.000629868358373642,
                    0.003111686557531357,
                    0.008021743968129158,
                    0.01494121178984642,
                    0.02318308874964714,
                    0.03208562359213829,
                    0.041176918894052505,
                    0.050157420337200165,
                    0.05879710242152214,
                    0.06683902442455292,
                    0.07394854724407196,
                    0.07971887290477753,
                    0.0837208479642868,
                    0.08556227385997772,
                    0.08492876589298248,
                    0.08161596953868866,
                    0.075581394135952,
                    0.06700710952281952,
                    0.05632743984460831,
                    0.04420240968465805,
                    0.03145546466112137,
                    0.01898280531167984,
                    0.0076361726969480515,
                    -0.0018939371220767498,
                    -0.009164310991764069,
                    -0.014022529125213623,
                    -0.016606876626610756,
                    -0.017303403466939926,
                    -0.016666846349835396,
                    -0.015320740640163422,
                    -0.013852625153958797,
                    -0.012721646577119827,
                    -0.012194857001304626,
                    -0.012324806302785873,
                    -0.012988177128136158,
                    -0.01398154255002737,
                    -0.015124223195016384,
                    -0.016310689970850945,
                    -0.017460394650697708,
                    -0.018395252525806427,
                    -0.018809543922543526,
                    -0.018408402800559998,
                    -0.017070967704057693,
                    -0.014891665428876877,
                    -0.01210876740515232,
                    -0.00900796428322792,
                    -0.005858888849616051,
                    -0.0028937114402651787,
                    -0.0003068116493523121,
                    0.0017541623674333096,
                    0.0032013305462896824,
                    0.0040009221993386745,
                    0.004159561358392239,
                    0.0037238914519548416,
                    0.0027893162332475185,
                    0.0014992086216807365,
                    2.2930093109607697e-05,
                    -0.0014821835793554783,
                    -0.0029063336551189423,
                    -0.004201238509267569,
                    -0.005371606908738613,
                    -0.006461471784859896,
                    -0.007540025748312473,
                    -0.008675768971443176,
                    -0.009903404861688614,
                    -0.011204684153199196,
                    -0.01252154540270567,
                    -0.013796635903418064,
                    -0.015012300573289394,
                    -0.016211768612265587,
                    -0.017505547031760216,
                    -0.019063521176576614,
                    -0.021097151562571526,
                    -0.02383117564022541,
                    -0.027440790086984634,
                    -0.03195951133966446,
                    -0.03722098469734192,
                    -0.04286213591694832,
                    -0.04833264276385307,
                    -0.052854377776384354,
                    -0.05537625774741173,
                    -0.05469949543476105,
                    -0.0498708039522171,
                    -0.040651533752679825,
                    -0.027762746438384056,
                    -0.012760487385094166,
                    0.0023988743778318167,
                    0.015868939459323883,
                    0.02628309652209282,
                    0.03294143080711365,
                    0.0358307808637619,
                    0.03548707440495491,
                    0.03275400027632713,
                    0.028522003442049026,
                    0.023517373949289322,
                    0.018180498853325844,
                    0.012649445794522762,
                    0.006833635736256838,
                    0.0005488570313900709,
                    -0.006310005206614733,
                    -0.013622595928609371,
                    -0.021005501970648766,
                    -0.02789139188826084,
                    -0.0336589589715004,
                    -0.03775568678975105,
                    -0.039793554693460464,
                    -0.039603449404239655,
                    -0.03723753243684769,
                    -0.03293388709425926,
                    -0.027065493166446686,
                    -0.020077891647815704,
                    -0.012414878234267235,
                    -0.00445164181292057,
                    0.0035338103771209717,
                    0.011337535455822945,
                    0.018773723393678665,
                    0.025625264272093773,
                    0.03162308782339096,
                    0.03644942492246628,
                    0.039757732301950455,
                    0.041210491210222244,
                    0.04056069999933243,
                    0.03780703991651535,
                    0.03334025293588638,
                    0.027911458164453506,
                    0.022406205534934998,
                    0.017605513334274292,
                    0.014090237207710743,
                    0.01227592583745718,
                    0.012449237518012524,
                    0.014715563505887985,
                    0.01890508458018303,
                    0.02454352378845215,
                    0.030922213569283485,
                    0.03722841665148735,
                    0.0426885262131691,
                    0.04669138789176941,
                    0.04886917769908905,
                    0.04912177100777626,
                    0.04758327826857567,
                    0.04455156251788139,
                    0.04041214659810066,
                    0.0355716273188591,
                    0.030401647090911865,
                    0.025202488526701927,
                    0.020196817815303802,
                    0.015535209327936172,
                    0.011291097849607468,
                    0.007460711523890495,
                    0.003983352333307266,
                    0.0007659979164600372,
                    -0.0023034904152154922,
                    -0.005347121506929398,
                    -0.00847636628895998,
                    -0.011767679825425148,
                    -0.015258119441568851,
                    -0.018967611715197563,
                    -0.022932257503271103,
                    -0.027221012860536575,
                    -0.031898368149995804,
                    -0.036921724677085876,
                    -0.04202211648225784,
                    -0.04662053659558296,
                    -0.0498141348361969,
                    -0.050527423620224,
                    -0.04786112159490585,
                    -0.041446343064308167,
                    -0.03160105645656586,
                    -0.01926984079182148,
                    -0.00580955483019352,
                    0.007325938902795315,
                    0.018939480185508728,
                    0.028371192514896393,
                    0.035582564771175385,
                    0.04101986438035965,
                    0.04535422474145889,
                    0.04921996593475342,
                    0.05301881581544876,
                    0.05681304633617401,
                    0.06032620370388031,
                    0.06304948031902313,
                    0.0643935576081276,
                    0.06381577998399734,
                    0.060903437435626984,
                    0.055423613637685776,
                    0.04734606668353081,
                    0.03684334456920624,
                    0.024275369942188263,
                    0.01016276702284813,
                    -0.004855193197727203,
                    -0.02008115127682686,
                    -0.03482886776328087,
                    -0.0484856478869915,
                    -0.060562457889318466,
                    -0.07073771208524704,
                    -0.07888710498809814,
                    -0.08507444709539413,
                    -0.08949856460094452,
                    -0.09241750091314316,
                    -0.09407608211040497,
                    -0.09465962648391724,
                    -0.09428143501281738,
                    -0.09299474954605103,
                    -0.09081999957561493,
                    -0.087785504758358,
                    -0.08397161960601807,
                    -0.07953527569770813,
                    -0.07470018416643143,
                    -0.06971486657857895,
                    -0.06479202210903168,
                    -0.06005869805812836,
                    -0.05554695799946785,
                    -0.0512261800467968,
                    -0.04705243557691574,
                    -0.04300513118505478,
                    -0.03909379243850708,
                    -0.03533761575818062,
                    -0.031734075397253036,
                    -0.028235768899321556,
                    -0.024746568873524666,
                    -0.02113776095211506,
                    -0.01727801188826561,
                    -0.01306732464581728,
                    -0.008470332249999046,
                    -0.0035370085388422012,
                    0.0016139112412929535,
                    0.006835488602519035,
                    0.011976642534136772,
                    0.01688913255929947,
                    0.02143120765686035,
                    0.02546670287847519,
                    0.028866373002529144,
                    0.03151562437415123,
                    0.03332449495792389,
                    0.03424520790576935,
                    0.034297700971364975,
                    0.033583227545022964,
                    0.03227142244577408,
                    0.03056718409061432,
                    0.028667975217103958,
                    0.02672228030860424,
                    0.024795792996883392,
                    0.022836996242403984,
                    0.020661458373069763,
                    0.018016600981354713,
                    0.014724770560860634,
                    0.010804455727338791,
                    0.006493931636214256,
                    0.0021908991038799286,
                    -0.0016399770975112915,
                    -0.0045491792261600494,
                    -0.0061478763818740845,
                    -0.006112437695264816,
                    -0.004179820418357849,
                    -0.00017914175987243652,
                    0.00589573010802269,
                    0.013821244239807129,
                    0.023131288588047028,
                    0.033149752765893936,
                    0.043059032410383224,
                    0.052022770047187805,
                    0.059352047741413116,
                    0.0646655336022377,
                    0.06798791885375977,
                    0.06972721964120865,
                    0.07051293551921844,
                    0.07097773253917694,
                    0.07159535586833954,
                    0.07260356098413467,
                    0.07397840917110443,
                    0.07544495910406113,
                    0.07653539627790451,
                    0.07669574022293091,
                    0.07541222870349884,
                    0.07231079787015915,
                    0.06720928847789764,
                    0.060141339898109436,
                    0.05136293172836304,
                    0.04132872819900513,
                    0.03063129261136055,
                    0.01991383731365204,
                    0.00978032685816288,
                    0.0007251603528857231,
                    -0.006908915005624294,
                    -0.012943476438522339,
                    -0.01735108718276024,
                    -0.020227357745170593,
                    -0.02175886556506157
                ]
            },
            "systolicPeaks": {
                "peaksTimeNanos": [
                    1746908647058335000,
                    1746908647562556718,
                    1746908648090174535,
                    1746908649321270086,
                    1746908649967335000,
                    1746908650710356540,
                    1746908651352261540,
                    1746908651997549440,
                    1746908652631335000
                ]
            },
            "steps": {
                "timestampStart": 1746908652061326,
                "samplingFrequency": 0.20000000298023224,
                "values": [
                    7
                ]
            }
        }
    }
]